tangbao/__init__.py
tangbao/apollo.py
tangbao/azure.py
tangbao/config.py
tangbao/parse_docs.py
tangbao/rerankers.py
tangbao/retrievers.py
tangbao/ui.py
tangbao/utils.py
tangbao/certs/apimgmt.crt
tangbao-0.3.19.dist-info/licenses/LICENSE
tangbao-0.3.19.dist-info/METADATA
tangbao-0.3.19.dist-info/WHEEL
tangbao-0.3.19.dist-info/top_level.txt
tangbao-0.3.19.dist-info/RECORD
