Metadata-Version: 2.4
Name: tangbao
Version: 0.3.19
Summary: Framework for building LLM-based apps in Boehringer Ingelheim
Author-email: Steven Brooks <steven.brooks@boehringer.com>, Pietro Mascheroni <pietro.mascheroni@boehringer.com>
Classifier: Programming Language :: Python :: 3
Classifier: License :: OSI Approved :: MIT License
Classifier: Operating System :: OS Independent
Requires-Python: >=3.9
License-File: LICENSE
Requires-Dist: python-dotenv==1.0.1
Requires-Dist: requests>=2.31.0
Requires-Dist: langchain==0.3.3
Requires-Dist: langchain-community==0.3.2
Requires-Dist: unstructured>=0.13.2
Requires-Dist: openai>=1.55.3
Requires-Dist: retrying==1.3.4
Requires-Dist: oauthlib==3.2.2
Requires-Dist: requests-oauthlib==2.0.0
Requires-Dist: bm25s==0.2.5
Requires-Dist: httpx-auth==0.22.0
Requires-Dist: litellm[proxy]==1.75.2
Provides-Extra: rerank
Requires-Dist: torch==2.5.1; extra == "rerank"
Requires-Dist: sentence-transformers==3.3.1; extra == "rerank"
Provides-Extra: ui
Requires-Dist: streamlit>=1.31.0; extra == "ui"
Dynamic: license-file
